{"0_dowload_data": {"lst_update": "2023-07-20 17:31:28 UTC", "lst_date": "20 Jul 23", "from": "py", "msg_txt": ""}, "1_compute_mozaic_allocation": {"lst_update": "2023-07-20 17:31:35 UTC", "lst_date": "20 Jul 23", "from": "py", "msg_txt": ""}, "2_compute_mozaic_bt_ytd": {"lst_update": "2023-07-20 17:31:47 UTC", "lst_date": "20 Jul 23", "from": "py", "msg_txt": ""}, "3_0_orderbook_forwebsite": {"lst_update": "2023-07-20 17:32:11 UTC", "lst_date": "2023-07-20", "from": "py", "msg_txt": "NAV, 20Jul@17:31\nAUM_t: 836.27, AUM_tm1: 830.84\nP&L B:+5.4$(+0.7%), BTC: 29704.2$(-0.7%)\n\nPerformance attribution\nPnL: +5.4$, PnL_tm1: +3.6$, PnL_trd: +1.9$, tc_usdt: 0.02, \u03b5: 0.04\nd_t: 20Jul 17:31, d_tm1: 19Jul 23:59, d_trd: 20Jul 14:12\n\nWallet:\nas of: 20 Jul 17:31\nAUMs: $ 836, P&L[U]: $ 63.0\nsum w%: 39%, sum w%>0: 54%, sum w%<0: -15%\n--------------------------\nPerformance report\n--------------------------\nBinance Official\n1D: +0.7%, WtD: +1.6%, 7D: +1.2%, MtD: -1.4%, s. 18Feb23: -3.7%\nBacktest\n1D: +0.6%, WtD: +1.2%, 7D: -0.9%, MtD: -4.3%, s. 18Feb23: -14.5%\nBitcoin\n1D: -0.7%, WtD: -1.7%, 7D: -5.6%, MtD: -2.5%, s. 18Feb23: +20.6%\nCryptosAll\n1D: +0.8%, WtD: +1.8%, 7D: -3.4%, MtD: +9.6%, s. 18Feb23: -7.1%\ntracking_error\n1D: +0.1%, WtD: +0.3%, 7D: +2.1%, MtD: +3.0%, s. 18Feb23: +12.7%\n----------------------------"}, "5_execute_futures": {"lst_update": "2023-07-20 14:16:28 UTC", "lst_date": "2023-07-20", "from": "py", "msg_txt": "EXECUTION TRADES OK:\nscripts :2023-07-20 14:11:03 UTC:0_dowload_data | 2023-07-20 14:11:10 UTC:1_compute_mozaic_allocation | 20 Jul 2023 14:16:5_execute_futures\n***************************\nTrades of the day\nin$\nas of: 20Jul 14:11>>14:16 (#trades: 9)\ntrade net: $ -33 (-3%), trade gross: $ 124 (14%), BUY: $ 45 (5%), SELL: $ -78 (-9%)\nfees: $ 0.02 (1.6bp)"}, "_2_get_lastmcap_update": {"lst_update": "2023-07-20 17:33:33 UTC", "lst_date": "20 Jul 2023", "from": "py", "msg_txt": ""}, "6_post_trades": {"lst_update": "2023-07-10 13:51:38 UTC", "lst_date": "10Jul 13:46>>13:49", "from": "py", "msg_txt": "Trades of the day\nin$\nas of: 10Jul 13:46>>13:49, trade net: $ 51, trade gross: $ 190, BUY: $ 120, SELL: $ -70, fees: $ 0.03\ni%$\nas of: #trades: 14, trade net: 6%, trade gross: 24%, BUY: 15%, SELL: -8%, fees: 1.6bp\nin$\nPnLvsLast: 0.0, PnLvsArrival: 0.1, realizedPnl: 4.9\nin bp vs. 189 traded\nPnLvsLast: 0 bp, PnLvsArrival: 4 bp, realizedPnl: 257 bp\nin bp vs. 785 AUMs\nPnLvsLast: 0 bp, PnLvsArrival: 1 bp, realizedPnl: 62 bpTrades: \nFilled #14\n______________________________________________\n                 | Value$ | PnL Arrival/Last \n______________________________________________\nADA:+28@0.2862 | +8$ | 0.02/0.01\nAVAX:+2@13.31 | +27$ | 0.05/0.01\nBCH:-0.04@269.98 | -9$ | 0/-0.01\nBNB:+0.08@242.26 | +19$ | 0.02/0.01\nDOGE:+93@0.0646 | +6$ | 0.01/0\nETH:-0@1864.18 | -6$ | -0/0\nLINK:-0.91@6.111 | -6$ | -0.01/-0\nLTC:-0.14@94.95 | -14$ | -0.01/0.01\nMATIC:+36@0.7072 | +25$ | -0/-0.03\nSOL:+1@20.782 | +21$ | 0.04/0.01\nTRX:+110@0.07709 | +8$ | 0.01/-0.01\nXLM:-67@0.09833 | -7$ | -0.01/0\nXMR:-0.17@164.94 | -29$ | -0.04/0\nXRP:+11.5@0.4716 | +5$ | -0/-0"}, "8_bt_btcXalt": {"lst_update": "2023-07-10 13:52:05 UTC", "lst_date": "20230710", "from": "py", "msg_txt": "ok"}, "9_bt_recap": {"lst_update": "2023-07-04 17:29:43 UTC", "lst_date": "20230703", "from": "ipynb", "msg_txt": "ok"}}